textboost/__init__.py
textboost/main.py
textboost-0.1.1.dist-info/LICENSE
textboost-0.1.1.dist-info/METADATA
textboost-0.1.1.dist-info/WHEEL
textboost-0.1.1.dist-info/entry_points.txt
textboost-0.1.1.dist-info/top_level.txt
textboost-0.1.1.dist-info/RECORD
