Metadata-Version: 2.1
Name: textboost
Version: 0.1.1
Summary: A tool leveraged by ML to aid the reading experience through bionic reading.
Home-page: https://github.com/boushrabettir/textboost
Author: Boushra Bettir
Author-email: boushra.bettir04@csu.fullerton.edu
Classifier: License :: OSI Approved :: MIT License
Classifier: Programming Language :: Python :: 3
Classifier: Programming Language :: Python :: 3.6
Classifier: Programming Language :: Python :: 3.7
Classifier: Programming Language :: Python :: 3.8
Classifier: Programming Language :: Python :: 3.9
Requires-Python: >=3.6
License-File: LICENSE
Requires-Dist: nltk (>=3.8.1)
Requires-Dist: numpy (>=1.23.5)
Requires-Dist: scikit-learn (>=1.2.2)
Requires-Dist: textual (>=0.30.0)
Requires-Dist: transformers (>=4.31.0)
Requires-Dist: tensorflow (>=2.13.0)
